hdb/__init__.py
hdb/hdb.py
hdb-0.1.2.dist-info/METADATA
hdb-0.1.2.dist-info/WHEEL
hdb-0.1.2.dist-info/top_level.txt
hdb-0.1.2.dist-info/RECORD
