Metadata-Version: 2.1
Name: hdb
Version: 0.1.2
Summary: HobbitDB - persistent Python dictionaries
Home-page: 
Author: Chris Varga
Author-email: 
Keywords: hdb hobbit database persistent dictionary json
Classifier: Programming Language :: Python
Classifier: License :: OSI Approved :: MIT License
Classifier: Operating System :: OS Independent
